odoo/addons/web_pwa_customize/README.rst
odoo/addons/web_pwa_customize/__init__.py
odoo/addons/web_pwa_customize/__manifest__.py
odoo/addons/web_pwa_customize/controllers/__init__.py
odoo/addons/web_pwa_customize/controllers/webmanifest.py
odoo/addons/web_pwa_customize/i18n/es.po
odoo/addons/web_pwa_customize/i18n/it.po
odoo/addons/web_pwa_customize/i18n/web_pwa_customize.pot
odoo/addons/web_pwa_customize/models/__init__.py
odoo/addons/web_pwa_customize/models/res_config_settings.py
odoo/addons/web_pwa_customize/readme/CONFIGURE.md
odoo/addons/web_pwa_customize/readme/CONTEXT.md
odoo/addons/web_pwa_customize/readme/CONTRIBUTORS.md
odoo/addons/web_pwa_customize/readme/DESCRIPTION.md
odoo/addons/web_pwa_customize/static/description/icon.png
odoo/addons/web_pwa_customize/static/description/index.html
odoo/addons/web_pwa_customize/tests/__init__.py
odoo/addons/web_pwa_customize/tests/test_web_pwa_customize.py
odoo/addons/web_pwa_customize/views/res_config_settings_views.xml
odoo_addon_web_pwa_customize-18.0.1.0.0.2.dist-info/METADATA
odoo_addon_web_pwa_customize-18.0.1.0.0.2.dist-info/WHEEL
odoo_addon_web_pwa_customize-18.0.1.0.0.2.dist-info/top_level.txt
odoo_addon_web_pwa_customize-18.0.1.0.0.2.dist-info/RECORD
